[
  {
    "id": 1,
    "name": "Smart AI Assistant",
    "category": "AI Consumer Products",
    "price": 299.99,
    "description": "An intelligent virtual assistant for everyday tasks"
  },
  {
    "id": 2,
    "name": "Voice Recognition Module",
    "category": "AI Consumer Products",
    "price": 149.99,
    "description": "Advanced voice recognition technology for smart devices"
  },
  {
    "id": 3,
    "name": "AI Edge Processor",
    "category": "AI Consumer Products",
    "price": 499.99,
    "description": "Process AI workloads locally on your device"
  },
  {
    "id": 4,
    "name": "TPU Accelerator Card",
    "category": "Hardware",
    "price": 799.99,
    "description": "Tensor Processing Unit for accelerated machine learning"
  },
  {
    "id": 5,
    "name": "Neural Network Server",
    "category": "Hardware",
    "price": 1299.99,
    "description": "Dedicated server for running neural networks"
  },
  {
    "id": 6,
    "name": "Quantum Computing Module",
    "category": "Advanced Computing",
    "price": 4999.99,
    "description": "Experimental quantum computing capabilities"
  },
  {
    "id": 7,
    "name": "AI Development Kit",
    "category": "Developer Tools",
    "price": 399.99,
    "description": "Complete toolkit for AI application development"
  },
  {
    "id": 8,
    "name": "Semiconductor Design Suite",
    "category": "Developer Tools",
    "price": 899.99,
    "description": "Professional tools for semiconductor design"
  },
  {
    "id": 9,
    "name": "Natural Language Processor",
    "category": "AI Components",
    "price": 249.99,
    "description": "Process and understand human language in your applications"
  },
  {
    "id": 10,
    "name": "Computer Vision System",
    "category": "AI Components",
    "price": 349.99,
    "description": "Add visual recognition capabilities to your projects"
  }
]